setup.py
learning_just_chill/Binomialdistribution.py
learning_just_chill/Gaussiandistribution.py
learning_just_chill/Generaldistribution.py
learning_just_chill/__init__.py
learning_just_chill.egg-info/PKG-INFO
learning_just_chill.egg-info/SOURCES.txt
learning_just_chill.egg-info/dependency_links.txt
learning_just_chill.egg-info/not-zip-safe
learning_just_chill.egg-info/top_level.txt